README.rst
mdx_graphviz.py
setup.py
python_markdown_graphviz.egg-info/PKG-INFO
python_markdown_graphviz.egg-info/SOURCES.txt
python_markdown_graphviz.egg-info/dependency_links.txt
python_markdown_graphviz.egg-info/requires.txt
python_markdown_graphviz.egg-info/top_level.txt