Metadata-Version: 1.0
Name: python-markdown-graphviz
Version: 1.0.1
Summary: Graphviz extension for python-markdown
Home-page: https://github.com/liuyug/python-markdown-graphviz.git
Author: Yugang LIU
Author-email: liuyug@gmail.com
License: MIT
Platform: UNKNOWN
